setup.py
TurboHtmlPy.egg-info/PKG-INFO
TurboHtmlPy.egg-info/SOURCES.txt
TurboHtmlPy.egg-info/entry_points.txt
TurboHtmlPy.egg-info/not-zip-safe
TurboHtmlPy.egg-info/requires.txt
TurboHtmlPy.egg-info/top_level.txt
turbohtmlpy/__init__.py
turbohtmlpy/templater.py
turbohtmlpy/tests_doctests.py
turbohtmlpy/examples/__init__.py
turbohtmlpy/examples/controllers.py
turbohtmlpy/examples/real/__init__.py
turbohtmlpy/examples/tg_quickstart/__init__.py
