Metadata-Version: 1.0
Name: TurboHtmlPy
Version: 0.4
Summary: Template plugin for TurboGears and Buffet
Home-page: http://dwayneb.free.fr/turbohtmlpy/
Author: David Bernard
Author-email: dwayne@java-fan.com
License: LGPL
Platform: UNKNOWN
Classifier: Development Status :: 4 - Beta
Classifier: Operating System :: OS Independent
Classifier: Programming Language :: Python
Classifier: Intended Audience :: Developers
Classifier: License :: OSI Approved :: GNU Library or Lesser General Public License (LGPL)
Classifier: Topic :: Software Development :: Libraries :: Python Modules
Classifier: Topic :: Internet :: WWW/HTTP :: Dynamic Content
